subrosa.py
subrosa-0.1.0.dist-info/DESCRIPTION.rst
subrosa-0.1.0.dist-info/METADATA
subrosa-0.1.0.dist-info/RECORD
subrosa-0.1.0.dist-info/WHEEL
subrosa-0.1.0.dist-info/metadata.json
subrosa-0.1.0.dist-info/top_level.txt
