Metadata-Version: 1.1
Name: subrosa
Version: 0.1.0
Summary: Shamir's Secret Sharing
Home-page: https://github.com/DasIch/subrosa/
Author: Daniel Neuhäuser
Author-email: ich@danielneuhaeuser.de
License: UNKNOWN
Platform: UNKNOWN
Classifier: License :: OSI Approved :: BSD License
Classifier: Programming Language :: Python :: 3.4
Classifier: Programming Language :: Python :: 3.5
Classifier: Programming Language :: Python :: Implementation :: CPython
